{
	"name": "helloworld",
	"properties": {
		"folder": {
			"name": "_adhoc"
		},
		"nbformat": 4,
		"nbformat_minor": 2,
		"bigDataPool": {
			"referenceName": "threetwo",
			"type": "BigDataPoolReference"
		},
		"sessionProperties": {
			"driverMemory": "28g",
			"driverCores": 4,
			"executorMemory": "28g",
			"executorCores": 4,
			"numExecutors": 2,
			"runAsWorkspaceSystemIdentity": false,
			"conf": {
				"spark.dynamicAllocation.enabled": "false",
				"spark.dynamicAllocation.minExecutors": "2",
				"spark.dynamicAllocation.maxExecutors": "2",
				"spark.autotune.trackingId": "5f4937a4-df05-4219-a8cd-b975adc8b239"
			}
		},
		"metadata": {
			"saveOutput": true,
			"enableDebugMode": false,
			"kernelspec": {
				"name": "synapse_pyspark",
				"display_name": "python"
			},
			"language_info": {
				"name": "python"
			},
			"a365ComputeOptions": {
				"id": "/subscriptions/e4e06275-58d1-4081-8f1b-be12462eb701/resourceGroups/wplushiramsynapse/providers/Microsoft.Synapse/workspaces/wplushiramsynapse/bigDataPools/threetwo",
				"name": "threetwo",
				"type": "Spark",
				"endpoint": "https://wplushiramsynapse.dev.azuresynapse.net/livyApi/versions/2019-11-01-preview/sparkPools/threetwo",
				"auth": {
					"type": "AAD",
					"authResource": "https://dev.azuresynapse.net",
					"authHeader": null
				},
				"sparkVersion": "3.2",
				"nodeCount": 5,
				"cores": 4,
				"memory": 28,
				"extraHeader": null
			},
			"sessionKeepAliveTimeout": 30
		},
		"cells": [
			{
				"cell_type": "code",
				"source": [
					"print('hello world')"
				]
			}
		]
	}
}