{
	"name": "relationship-xnsxsrfndl",
	"properties": {
		"Name": "relationship-xnsxsrfndl",
		"EntityType": "RELATIONSHIP",
		"Namespace": {
			"DatabaseName": "Manufacturing_qwg"
		},
		"Origin": {
			"Type": "SPARK"
		},
		"FromTableName": "ManufacturingProduct",
		"ToTableName": "Item",
		"ColumnRelationshipInformations": [
			{
				"FromColumnName": "ProductId",
				"ToColumnName": "ProductId"
			}
		],
		"RelationshipType": 0,
		"Properties": {
			"DerivedModelRelationshipInfo": "{\"baseRelationship\":{\"fromEntity\":\"ManufacturingProduct.cdm.json/ManufacturingProduct\",\"toEntity\":\"Item.cdm.json/Item\",\"joinPairs\":[{\"fromAttribute\":\"ProductId\",\"toAttribute\":\"ProductId\"}]}}"
		},
		"PublishStatus": "PUBLISHED",
		"ObjectVersion": 1,
		"ObjectId": "7d0e421f-dabb-4e7e-a349-244fd33fb2fc"
	},
	"type": "RELATIONSHIP"
}